README.txt
setup.py
Django_MobilityHelpers.egg-info/PKG-INFO
Django_MobilityHelpers.egg-info/SOURCES.txt
Django_MobilityHelpers.egg-info/dependency_links.txt
Django_MobilityHelpers.egg-info/not-zip-safe
Django_MobilityHelpers.egg-info/requires.txt
Django_MobilityHelpers.egg-info/top_level.txt
mobilityhelpers/__init__.py
mobilityhelpers/middleware/__init__.py