Metadata-Version: 1.1
Name: Django-MobilityHelpers
Version: 0.3.0
Summary: Simple middleware and helper function to help handle request from mobile devices.
Home-page: https://github.com/weholt/django-mobilityhelpers
Author: Thomas Weholt
Author-email: thomas@weholt.org
License: Modified BSD
Keywords: django middleware mobile devices
Platform: UNKNOWN
Classifier: Development Status :: 4 - Beta
Classifier: Intended Audience :: Developers
Classifier: Framework :: Django
Classifier: License :: OSI Approved :: BSD License
Classifier: Programming Language :: Python :: 3.3
Classifier: Programming Language :: Python :: 2.7
Classifier: Operating System :: OS Independent
Classifier: Programming Language :: Python
Classifier: Topic :: Database
